pydq/__init__.py
pydq/helpers.py
pydq/cloud/__init__.py
pydq/cloud/buffered_ddb.py
pydq/cloud/dynamodb.py
pydq/cloud/kafka.py
pydq/local/__init__.py
pydq/local/postgres.py
pydq/local/sqlite.py
pydq-0.1.20.dist-info/LICENSE
pydq-0.1.20.dist-info/METADATA
pydq-0.1.20.dist-info/WHEEL
pydq-0.1.20.dist-info/top_level.txt
pydq-0.1.20.dist-info/RECORD
