Metadata-Version: 2.1
Name: pydq
Version: 0.1.20
Summary: Python library for managing and persisting named Python Queues with a variety of backend choices
Home-page: https://gitlab.com/anfreitas/dq
Author: Andrew Freitas
Author-email: andrewfreitas09@gmail.com
License: UNKNOWN
Platform: UNKNOWN
Classifier: Programming Language :: Python :: 3
Classifier: License :: OSI Approved :: MIT License
Classifier: Operating System :: OS Independent
Provides-Extra: aws
Requires-Dist: boto3 ; extra == 'aws'
Provides-Extra: pandas
Requires-Dist: pandas ; extra == 'pandas'
